LICENSE
MANIFEST.in
README.md
setup.py
src/django_front_door.egg-info/PKG-INFO
src/django_front_door.egg-info/SOURCES.txt
src/django_front_door.egg-info/dependency_links.txt
src/django_front_door.egg-info/not-zip-safe
src/django_front_door.egg-info/requires.txt
src/django_front_door.egg-info/top_level.txt
src/front_door/__init__.py
src/front_door/checker.py
src/front_door/conf.py
src/front_door/exception.py
src/front_door/middleware.py
src/front_door/router.py
src/front_door/rules.py
src/front_door/utils.py
src/front_door/contrib/__init__.py
src/front_door/contrib/constance.py
src/front_door/contrib/panel.py
src/front_door/contrib/management/__init__.py
src/front_door/contrib/management/commands/__init__.py
src/front_door/contrib/management/commands/frontdoor.py
src/front_door/contrib/templates/frontdoor/smart_panel.html