Metadata-Version: 2.1
Name: django-front-door
Version: 0.10.0
Summary: UNKNOWN
Home-page: https://github.com/saxix/django-front-door
Author: sax
Author-email: s.apostolico@gmail.com
License: MIT
Download-URL: https://github.com/saxix/django-front-door
Platform: any
Classifier: Environment :: Web Environment
Classifier: Framework :: Django
Classifier: Operating System :: OS Independent
Classifier: Framework :: Django :: 3.2
Classifier: Framework :: Django :: 4.0
Classifier: Framework :: Django :: 4.1
Classifier: Programming Language :: Python :: 3.9
Classifier: Programming Language :: Python :: 3.10
Classifier: Intended Audience :: Developers
Provides-Extra: test
Provides-Extra: dev
Provides-Extra: docs
Provides-Extra: constance
Provides-Extra: redis
Provides-Extra: ua
